<?xml version="1.0" encoding="UTF-8"?>
<beans xmlns="http://www.springframework.org/schema/beans"
	xmlns:xsi="http://www.w3.org/2001/XMLSchema-instance"
	xsi:schemaLocation="http://www.springframework.org/schema/beans 
		http://www.springframework.org/schema/beans/spring-beans.xsd">

     <bean id="helloWorld1" factory-method="getHelloWorld"
          class="test.HelloWorld">
          <constructor-arg ref="fileHello"/>
     </bean>
     
     <bean id="helloWorld2" factory-bean="helloWorldFactory"
     		factory-method="makeHelloWorld">
          <constructor-arg ref="fileHello"/>
     </bean>
     
     <bean id="helloWorldFactory" class="test.HelloWorld"/>
     
     <bean name="fileHello" class="test.FileHelloStrImpl">
          <constructor-arg>
               <value>helloworld.properties</value>
          </constructor-arg>  
     </bean>
     
</beans>